RegscorePy/__init__.py
RegscorePy/aic.py
RegscorePy/bic.py
RegscorePy/mallow.py
RegscorePy-1.0.data/scripts/aic.py
RegscorePy-1.0.data/scripts/bic.py
RegscorePy-1.0.data/scripts/mallow.py
RegscorePy-1.0.dist-info/DESCRIPTION.rst
RegscorePy-1.0.dist-info/METADATA
RegscorePy-1.0.dist-info/RECORD
RegscorePy-1.0.dist-info/WHEEL
RegscorePy-1.0.dist-info/metadata.json
RegscorePy-1.0.dist-info/top_level.txt
