Metadata-Version: 2.0
Name: RegscorePy
Version: 1.0
Summary: Useful score functions to assist regression model comparison
Home-page: https://github.com/UBC-MDS/regscore-py
Author: Ha Dinh, Simran Sethi, Ruoqi Xu
Author-email: dinhhn.ubc@gmail.com, simran.sethi@alumni.ubc.ca, rq658182@dal.ca
License: MIT
Download-URL: https://github.com/UBC-MDS/RegscorePy/archive/0.1.tar.gz
Keywords: aic,bic,mallows,regression-score,machine-learning
Platform: UNKNOWN
Requires-Dist: numpy
Requires-Dist: pandas
